mlflow_deploy_cli/__main__.py
mlflow_deploy_cli/template/Dockerfile.template
mlflow_deploy_cli/template/docker-compose.yml
mlflow_deploy_cli/utils/__init__.py
mlflow_deploy_cli/utils/utils.py
mlflow_deploy_cli-1.0.1.dist-info/WHEEL
mlflow_deploy_cli-1.0.1.dist-info/METADATA
mlflow_deploy_cli-1.0.1.dist-info/RECORD
