Metadata-Version: 2.1
Name: mlflow-deploy-cli
Version: 1.0.1
Summary: CLI for deployment of [MLFlow](https://mlflow.org/) with support for backend and artifact stores.
License: MIT
Author: Aleksandar Ivanovski
Author-email: aleksandar.ivanovski@codechem.com
Requires-Python: >=3.9,<4.0
Classifier: License :: OSI Approved :: MIT License
Classifier: Programming Language :: Python :: 3
Classifier: Programming Language :: Python :: 3.10
Classifier: Programming Language :: Python :: 3.9
Requires-Dist: prompt-toolkit (>=3.0.30,<4.0.0)
